{
  "main": {
    "id": "c0fe83eb42932a2d",
    "type": "split",
    "children": [
      {
        "id": "abedb2045cb6f122",
        "type": "tabs",
        "children": [
          {
            "id": "a790de4ed7167a09",
            "type": "leaf",
            "state": {
              "type": "markdown",
              "state": {
                "file": "Brouillon.md",
                "mode": "source",
                "source": false
              }
            }
          },
          {
            "id": "700db9e2cbe2c899",
            "type": "leaf",
            "state": {
              "type": "markdown",
              "state": {
                "file": "MCOT.md",
                "mode": "source",
                "source": false
              }
            }
          },
          {
            "id": "e8d1295c96b1de74",
            "type": "leaf",
            "state": {
              "type": "markdown",
              "state": {
                "file": "MCOT.md",
                "mode": "source",
                "source": false
              }
            }
          }
        ],
        "currentTab": 2
      }
    ],
    "direction": "vertical"
  },
  "left": {
    "id": "c759833ce1ed4f98",
    "type": "split",
    "children": [
      {
        "id": "1418a69d1822b796",
        "type": "tabs",
        "children": [
          {
            "id": "b53342462f094ace",
            "type": "leaf",
            "state": {
              "type": "file-explorer",
              "state": {
                "sortOrder": "alphabetical"
              }
            }
          },
          {
            "id": "1c4d683eb8a8d49c",
            "type": "leaf",
            "state": {
              "type": "search",
              "state": {
                "query": "",
                "matchingCase": false,
                "explainSearch": false,
                "collapseAll": false,
                "extraContext": false,
                "sortOrder": "alphabetical"
              }
            }
          },
          {
            "id": "1eb0204fd57c4a74",
            "type": "leaf",
            "state": {
              "type": "bookmarks",
              "state": {}
            }
          }
        ]
      }
    ],
    "direction": "horizontal",
    "width": 300
  },
  "right": {
    "id": "cac7d68219559364",
    "type": "split",
    "children": [
      {
        "id": "e398302e85582d47",
        "type": "tabs",
        "children": [
          {
            "id": "d0661ecb55a1ef0f",
            "type": "leaf",
            "state": {
              "type": "backlink",
              "state": {
                "file": "MCOT.md",
                "collapseAll": false,
                "extraContext": false,
                "sortOrder": "alphabetical",
                "showSearch": false,
                "searchQuery": "",
                "backlinkCollapsed": false,
                "unlinkedCollapsed": false
              }
            }
          },
          {
            "id": "c2e353042a1b8711",
            "type": "leaf",
            "state": {
              "type": "outgoing-link",
              "state": {
                "file": "MCOT.md",
                "linksCollapsed": false,
                "unlinkedCollapsed": true
              }
            }
          },
          {
            "id": "88ebe3cff6d9019e",
            "type": "leaf",
            "state": {
              "type": "tag",
              "state": {
                "sortOrder": "frequency",
                "useHierarchy": true
              }
            }
          },
          {
            "id": "e6498ce51d8461b0",
            "type": "leaf",
            "state": {
              "type": "outline",
              "state": {
                "file": "MCOT.md"
              }
            }
          }
        ],
        "currentTab": 1
      }
    ],
    "direction": "horizontal",
    "width": 300,
    "collapsed": true
  },
  "left-ribbon": {
    "hiddenItems": {
      "switcher:Ouvrir le sélecteur rapide": false,
      "graph:Ouvrir la vue graphique": false,
      "canvas:Créer une nouvelle toile": false,
      "daily-notes:Ouvrir la note quotidienne": false,
      "templates:Insérer le modèle": false,
      "command-palette:Ouvrir la palette de commandes": false
    }
  },
  "active": "e8d1295c96b1de74",
  "lastOpenFiles": [
    "Brouillon.md",
    "MCOT.md",
    "MCOT.pdf",
    "Ressources/Optimization by GRASP Greedy Randomized Adaptive Search Procedures (Mauricio G.C. Resende, Celso C. Ribeiro (auth.)) (Z-Library).pdf",
    "2023-10-17.md",
    "Ressources/Code pointage 2019-2021.pdf",
    "Ressources/en_2022 PK Code of Points - Judges' Scoring Sheets.pdf",
    "Ressources/en_1.1 - PK Code of Points 2022-2024 - Table of tricks 2023.pdf",
    "Ressources/Schema Theorem.pdf",
    "Ressources/Simulated Annealing and Boltzmann Machines A Stochastic Approach to Combinatorial Optimization and Neural Computing (Emile H. L. Aarts, Jan Korst) (Z-Library).pdf",
    "Ressources/Algorithms illuminated. Part 3. Greedy algorithms and dynamic programming (Roughgarden T) (Z-Library).pdf",
    "Ressources/Notation du score.pdf",
    "Ressources/PK-World-Ranking-2022.pdf",
    "diapo/images/lilou.jpg",
    "diapo/images/LILOUcases.png",
    "diapo/images/LILOUconstantes.png",
    "diapo/images/LILOUfreq&fitness.png",
    "diapo/images/freq&fitness.png",
    "diapo/images/constantes.png",
    "diapo/images/cases.png",
    "diapo/images/modeles.png",
    "Classes.canvas",
    "diapo/images/terrain.png",
    "diapo/images/Modèles.png",
    "Code/images/Image scoring réelle/all_images/freq.png.md",
    "[Code/images/1 Generation avec nv scoring/freq.png.md",
    "Readme.md",
    "Code/README.md",
    "Code-TIPE/README.md",
    "Python.md",
    "Python Classes.md",
    "Sans titre 1.canvas",
    "2023-06-22.md",
    "Sans titre.canvas"
  ]
}